{
"type": "FeatureCollection",
"name": "scz_mini_estadios",
"crs": { "type": "name", "properties": { "name": "urn:ogc:def:crs:OGC:1.3:CRS84" } },
"features": [
{ "type": "Feature", "properties": { "gid": 3, "objectid": 3, "id": false, "nombre": "Estadio Municipal  D-6", "distrito": 6, "uv": 204, "mz": "E", "calle": "Av. Bioceanica", "barrio": "B/Toborochi I", "iluminaci": "no", "parqueo": "si", "sist_rieg": "si", "capacidad": 5000, "point_x": 488808.63460200001, "point_y": 8039723.1894399999, "si": "SI", "no_": null, "p_x": -63.105556190920097, "p_y": -17.729633623657801 }, "geometry": { "type": "Point", "coordinates": [ -63.105556190920097, -17.729633623657801 ] } },
{ "type": "Feature", "properties": { "gid": 4, "objectid": 4, "id": false, "nombre": "Estadio Municipal  D-7", "distrito": 7, "uv": 86, "mz": "33", "calle": "C/8", "barrio": "B/Villa 1ro de mayo", "iluminaci": "no", "parqueo": "si", "sist_rieg": "si", "capacidad": 5000, "point_x": 486228.94194300001, "point_y": 8032172.2305899998, "si": "SI", "no_": null, "p_x": -63.129936910680001, "p_y": -17.797870907149399 }, "geometry": { "type": "Point", "coordinates": [ -63.129936910680001, -17.797870907149399 ] } },
{ "type": "Feature", "properties": { "gid": 5, "objectid": 5, "id": false, "nombre": "Estadio Municipal D-8", "distrito": 8, "uv": 149, "mz": "EQ", "calle": "C/Las Américas (6)", "barrio": "B/Zona Central (Plan 3000)", "iluminaci": "no", "parqueo": "si", "sist_rieg": "si", "capacidad": 5000, "point_x": 485927.97779899999, "point_y": 8028634.3263100004, "si": "SI", "no_": null, "p_x": -63.132800324640101, "p_y": -17.829847367566 }, "geometry": { "type": "Point", "coordinates": [ -63.132800324640101, -17.829847367566 ] } },
{ "type": "Feature", "properties": { "gid": 2, "objectid": 2, "id": false, "nombre": "Estadio Municipal D-5", "distrito": 5, "uv": 333, "mz": "E", "calle": " ", "barrio": "B/Bella Vista  Norte", "iluminaci": "no", "parqueo": " ", "sist_rieg": "si", "capacidad": 5000, "point_x": 480842.17511499999, "point_y": 8041291.43879, "si": "SI", "no_": null, "p_x": -63.1806808746949, "p_y": -17.715403673853199 }, "geometry": { "type": "Point", "coordinates": [ -63.1806808746949, -17.715403673853199 ] } },
{ "type": "Feature", "properties": { "gid": 1, "objectid": 1, "id": false, "nombre": "Estadio Municipal D-11", "distrito": 11, "uv": 1, "mz": "E", "calle": " ", "barrio": "B/Casco Viejo", "iluminaci": "si", "parqueo": "si", "sist_rieg": "si", "capacidad": 5000, "point_x": 481356.10094700003, "point_y": 8035100.4331200002, "si": "SI", "no_": null, "p_x": -63.1758885902304, "p_y": -17.7713675474807 }, "geometry": { "type": "Point", "coordinates": [ -63.1758885902304, -17.7713675474807 ] } },
{ "type": "Feature", "properties": { "gid": 6, "objectid": 6, "id": false, "nombre": "Estadio Municipal D-9", "distrito": 9, "uv": 131, "mz": "EQ", "calle": " ", "barrio": "B/Las Américas y 7mo anillo Santos Dumont", "iluminaci": "si", "parqueo": "si", "sist_rieg": "si", "capacidad": 7000, "point_x": 479465.38466600003, "point_y": 8025281.5151899997, "si": "SI", "no_": null, "p_x": -63.193821618550103, "p_y": -17.860101552534399 }, "geometry": { "type": "Point", "coordinates": [ -63.193821618550103, -17.860101552534399 ] } }
]
}
